quik_config/__init__.py
quik_config/main.py
quik_config-1.7.3.dist-info/METADATA
quik_config-1.7.3.dist-info/WHEEL
quik_config-1.7.3.dist-info/top_level.txt
quik_config-1.7.3.dist-info/RECORD
