Metadata-Version: 2.1
Name: quik-config
Version: 1.7.3
Summary: Project config files
Home-page: https://github.com/jeff-hykin/quik_config_python.git
Author: Jeff Hykin
Author-email: jeff.hykin@gmail.com
License: MIT
Platform: UNKNOWN
Requires-Python: >=3.6
